{
  "paper_title": "Geology, Chronology, and Sampling in the Zhaotong Basin",
  "methods_found": true,
  "methods": [
    {
      "method_name": "Sample Collection and Preparation",
      "description": "Collection and preparation of sediment samples from the Zhaotong Basin for various analyses.",
      "steps": [
        {
          "step_number": 1,
          "category": "data_fetch",
          "description": "A total of 337 samples with 5 cm intervals were collected from the STB section.",
          "searchable_summary": "collect sediment samples at 5 cm intervals",
          "inputs": [
            "STB section location"
          ],
          "outputs": [
            "337 sediment samples"
          ],
          "keywords": [
            "sample collection",
            "sediment"
          ]
        },
        {
          "step_number": 2,
          "category": "data_processing",
          "description": "32 samples were selected from different parts in the section for analysis.",
          "searchable_summary": "select 32 samples for analysis",
          "inputs": [
            "337 sediment samples"
          ],
          "outputs": [
            "32 selected samples"
          ],
          "keywords": [
            "sample selection",
            "analysis"
          ]
        },
        {
          "step_number": 3,
          "category": "data_processing",
          "description": "Twelve samples were chosen from the hominoid-bearing layer (8.70−9.25 m) for higher resolution record.",
          "searchable_summary": "select 12 samples from hominoid-bearing layer",
          "inputs": [
            "337 sediment samples"
          ],
          "outputs": [
            "12 high-resolution samples"
          ],
          "keywords": [
            "high-resolution",
            "hominoid-bearing layer"
          ]
        }
      ]
    },
    {
      "method_name": "X-Ray Diffraction (XRD) Analysis",
      "description": "Analysis of clay mineralogy and element geochemistry using X-ray diffraction.",
      "steps": [
        {
          "step_number": 1,
          "category": "data_processing",
          "description": "Clay fractions were separated following the methods described by Zhang and Guo (2013).",
          "searchable_summary": "separate clay fractions",
          "inputs": [
            "sediment samples"
          ],
          "outputs": [
            "clay fraction samples"
          ],
          "keywords": [
            "clay separation",
            "Zhang and Guo"
          ]
        },
        {
          "step_number": 2,
          "category": "data_analysis",
          "description": "Clay mineralogy was analyzed by X-ray diffraction using a PANAlytical diffractometer.",
          "searchable_summary": "analyze clay mineralogy with XRD",
          "inputs": [
            "clay fraction samples"
          ],
          "outputs": [
            "XRD analysis results"
          ],
          "keywords": [
            "XRD",
            "clay mineralogy"
          ]
        },
        {
          "step_number": 3,
          "category": "data_analysis",
          "description": "Four XRD runs were performed after air-drying, ethylene-glycol solvation, and heating at 300 °C or 550 °C.",
          "searchable_summary": "perform XRD runs under different conditions",
          "inputs": [
            "clay fraction samples"
          ],
          "outputs": [
            "XRD run results"
          ],
          "keywords": [
            "XRD",
            "ethylene-glycol",
            "heating"
          ]
        },
        {
          "step_number": 4,
          "category": "data_analysis",
          "description": "Identification of clay minerals was performed mainly according to the position of the (001) series of basal reflection.",
          "searchable_summary": "identify clay minerals from XRD diagrams",
          "inputs": [
            "XRD diagrams"
          ],
          "outputs": [
            "identified clay minerals"
          ],
          "keywords": [
            "clay identification",
            "basal reflection"
          ]
        },
        {
          "step_number": 5,
          "category": "data_analysis",
          "description": "Semi-quantitative estimates of peak area of the basal reflections for the main clay mineral groups were carried out using MacDiff software.",
          "searchable_summary": "estimate peak areas using MacDiff",
          "inputs": [
            "XRD diagrams"
          ],
          "outputs": [
            "semi-quantitative estimates"
          ],
          "keywords": [
            "MacDiff",
            "peak area estimation"
          ]
        }
      ]
    },
    {
      "method_name": "X-Ray Fluorescence (XRF) Analysis",
      "description": "Measurement of major elements in clay fractions using X-Ray Fluorescence.",
      "steps": [
        {
          "step_number": 1,
          "category": "data_processing",
          "description": "About 100 mg of pre-treated sediments were heated at 600 °C to obtain the loss on ignition (LOI).",
          "searchable_summary": "heat sediments to obtain LOI",
          "inputs": [
            "pre-treated sediments"
          ],
          "outputs": [
            "LOI data"
          ],
          "keywords": [
            "LOI",
            "heating"
          ]
        },
        {
          "step_number": 2,
          "category": "data_processing",
          "description": "Sediments were dissolved using a mixture of HNO3 + HF on a hot plate.",
          "searchable_summary": "dissolve sediments with HNO3 + HF",
          "inputs": [
            "heated sediments"
          ],
          "outputs": [
            "dissolved sediments"
          ],
          "keywords": [
            "dissolution",
            "HNO3",
            "HF"
          ]
        },
        {
          "step_number": 3,
          "category": "data_analysis",
          "description": "Eluted samples were diluted with 2% HNO3 for major-element measurement.",
          "searchable_summary": "dilute samples for XRF measurement",
          "inputs": [
            "dissolved sediments"
          ],
          "outputs": [
            "diluted samples"
          ],
          "keywords": [
            "dilution",
            "XRF"
          ]
        },
        {
          "step_number": 4,
          "category": "data_analysis",
          "description": "Major elements were measured by XRF using PANAlytical equipment.",
          "searchable_summary": "measure major elements with XRF",
          "inputs": [
            "diluted samples"
          ],
          "outputs": [
            "XRF measurement results"
          ],
          "keywords": [
            "XRF",
            "major elements"
          ]
        }
      ]
    },
    {
      "method_name": "Scanning Electron Microscope (SEM) Analysis",
      "description": "Determination of morphology, elements, and composition of clay fractions using SEM and EDX.",
      "steps": [
        {
          "step_number": 1,
          "category": "data_analysis",
          "description": "Morphology, elements, and composition of clay-fractions were determined by SEM and EDX.",
          "searchable_summary": "analyze clay fractions with SEM and EDX",
          "inputs": [
            "clay fractions"
          ],
          "outputs": [
            "SEM and EDX analysis results"
          ],
          "keywords": [
            "SEM",
            "EDX",
            "morphology"
          ]
        }
      ]
    },
    {
      "method_name": "Grain Size Analysis",
      "description": "Measurement of grain size distribution in sediment samples using a laser particle analyzer.",
      "steps": [
        {
          "step_number": 1,
          "category": "data_processing",
          "description": "All 337 samples were air dried in the laboratory.",
          "searchable_summary": "air dry sediment samples",
          "inputs": [
            "sediment samples"
          ],
          "outputs": [
            "air-dried samples"
          ],
          "keywords": [
            "air drying",
            "sediment"
          ]
        },
        {
          "step_number": 2,
          "category": "data_analysis",
          "description": "The distribution of grain size was measured using a Malvern Mastersizer-2000 laser particle analyzer.",
          "searchable_summary": "measure grain size with laser particle analyzer",
          "inputs": [
            "air-dried samples"
          ],
          "outputs": [
            "grain size distribution data"
          ],
          "keywords": [
            "grain size",
            "laser particle analyzer"
          ]
        }
      ]
    }
  ],
  "source_file": "paleoclimatology/papers-text.md/17558029.md",
  "extracted_at": "/Users/varun/git/paleopal/literature_library"
}