{
  "paper_title": "Assessing the Quality of Flux Chamber Measurements",
  "methods_found": true,
  "methods": [
    {
      "method_name": "Flux Chamber Installation and Measurement",
      "description": "This method describes the installation of flux chambers to measure ecosystem fluxes, addressing potential biases and disturbances caused by the installation process.",
      "steps": [
        {
          "step_number": 1,
          "category": "data_processing",
          "description": "Install 280 collars in the ground before starting the experiment to prevent leaking of air.",
          "searchable_summary": "install collars in the ground to prevent air leakage",
          "inputs": [
            "collars",
            "ground site"
          ],
          "outputs": [
            "installed collars"
          ],
          "keywords": [
            "flux chamber",
            "collar installation",
            "air leakage prevention"
          ]
        },
        {
          "step_number": 2,
          "category": "data_processing",
          "description": "Cut a shallow slit in the ground to tightly fit in collars.",
          "searchable_summary": "cut slit in ground for collar fitting",
          "inputs": [
            "ground site",
            "collars"
          ],
          "outputs": [
            "fitted collars"
          ],
          "keywords": [
            "collar fitting",
            "ground slit",
            "installation"
          ]
        },
        {
          "step_number": 3,
          "category": "validation",
          "description": "Assess the potential disturbance effects on soil and plant roots due to collar installation.",
          "searchable_summary": "evaluate disturbance effects from collar installation",
          "inputs": [
            "installed collars",
            "soil",
            "plant roots"
          ],
          "outputs": [
            "disturbance assessment"
          ],
          "keywords": [
            "disturbance effects",
            "soil",
            "plant roots"
          ]
        },
        {
          "step_number": 4,
          "category": "data_analysis",
          "description": "Compare chamber fluxes with eddy-covariance fluxes to evaluate the impact of installation artifacts.",
          "searchable_summary": "compare chamber and eddy-covariance fluxes",
          "inputs": [
            "chamber fluxes",
            "eddy-covariance fluxes"
          ],
          "outputs": [
            "comparison results"
          ],
          "keywords": [
            "flux comparison",
            "eddy-covariance",
            "installation artifacts"
          ]
        }
      ]
    },
    {
      "method_name": "Addressing Small-Scale Heterogeneity",
      "description": "This method addresses the small-scale heterogeneity in ecosystem measurements, which can affect the representativeness of chamber-based carbon flux measurements.",
      "steps": [
        {
          "step_number": 1,
          "category": "data_processing",
          "description": "Identify small-scale heterogeneity in the ecosystem, such as variations in soil temperature, soil moisture, and thaw depths.",
          "searchable_summary": "identify small-scale heterogeneity in ecosystem",
          "inputs": [
            "ecosystem data"
          ],
          "outputs": [
            "heterogeneity assessment"
          ],
          "keywords": [
            "small-scale heterogeneity",
            "soil temperature",
            "soil moisture",
            "thaw depths"
          ]
        },
        {
          "step_number": 2,
          "category": "data_analysis",
          "description": "Use more than one chamber to assess the mean and variance of surface fluxes to account for heterogeneity.",
          "searchable_summary": "use multiple chambers to assess flux mean and variance",
          "inputs": [
            "multiple chambers",
            "surface flux data"
          ],
          "outputs": [
            "mean and variance of fluxes"
          ],
          "keywords": [
            "multiple chambers",
            "flux assessment",
            "mean and variance"
          ]
        }
      ]
    }
  ],
  "source_file": "paleoclimatology/papers-text.md/235671124.md",
  "extracted_at": "/Users/varun/git/paleopal/literature_library"
}