{
  "paper_title": "Palynological Data Analysis in the Intra-Sudetic Basin",
  "methods_found": true,
  "methods": [
    {
      "method_name": "Palynological Data Collection and Processing",
      "description": "This method describes the collection and processing of palynological samples from coal seams and associated carbonaceous mudstones in the Czech part of the Intra-Sudetic Basin. The samples were used to recover dispersed miospores and pollen for further analysis.",
      "steps": [
        {
          "step_number": 1,
          "category": "data_fetch",
          "description": "Samples were macerated at Geoindustria Prague, an exploration company during the last few decades.",
          "searchable_summary": "macerate samples at Geoindustria Prague",
          "inputs": [
            "palynological samples"
          ],
          "outputs": [
            "macerated samples"
          ],
          "keywords": [
            "maceration",
            "Geoindustria Prague",
            "sample preparation"
          ]
        },
        {
          "step_number": 2,
          "category": "data_processing",
          "description": "Dispersed miospores and pollen were recovered by dissolving rocks in nitric acid for 24-48 hours and KOH for 1-2 hours and washed by water several times.",
          "searchable_summary": "dissolve rocks in nitric acid and KOH to recover miospores and pollen",
          "inputs": [
            "macerated samples",
            "nitric acid",
            "KOH"
          ],
          "outputs": [
            "recovered miospores and pollen"
          ],
          "keywords": [
            "dissolution",
            "nitric acid",
            "KOH",
            "miospores",
            "pollen"
          ]
        },
        {
          "step_number": 3,
          "category": "data_analysis",
          "description": "Miospores and pollen were classified according to the system of dispersed fossil spores suggested by Potonié & Kremp, Dettmann, and Smith & Butterworth.",
          "searchable_summary": "classify miospores and pollen using established systems",
          "inputs": [
            "recovered miospores and pollen"
          ],
          "outputs": [
            "classified miospores and pollen"
          ],
          "keywords": [
            "classification",
            "fossil spores",
            "Potonié & Kremp",
            "Dettmann",
            "Smith & Butterworth"
          ]
        }
      ]
    },
    {
      "method_name": "Palynological Data Analysis and Visualization",
      "description": "This method involves the analysis and visualization of palynological data to determine species richness and diversity patterns in the Intra-Sudetic Basin.",
      "steps": [
        {
          "step_number": 1,
          "category": "data_processing",
          "description": "Palynological data stored in the MafDat database have been exported to two Excel spreadsheets tables.",
          "searchable_summary": "export palynological data to Excel spreadsheets",
          "inputs": [
            "MafDat database"
          ],
          "outputs": [
            "Excel spreadsheets"
          ],
          "keywords": [
            "data export",
            "MafDat",
            "Excel"
          ]
        },
        {
          "step_number": 2,
          "category": "data_analysis",
          "description": "In the first table, palynospecies are plotted against the stratigraphic column with resolution of individual fossiliferous horizons.",
          "searchable_summary": "plot palynospecies against stratigraphic column",
          "inputs": [
            "Excel spreadsheet 1"
          ],
          "outputs": [
            "plotted palynospecies"
          ],
          "keywords": [
            "stratigraphic column",
            "palynospecies",
            "plotting"
          ]
        },
        {
          "step_number": 3,
          "category": "visualization",
          "description": "Construct diversity curves of palynological taxa by botanical groups as well as the curve of overall diversity of palynological taxa.",
          "searchable_summary": "construct diversity curves for palynological taxa",
          "inputs": [
            "plotted palynospecies"
          ],
          "outputs": [
            "diversity curves"
          ],
          "keywords": [
            "diversity curves",
            "botanical groups",
            "visualization"
          ]
        },
        {
          "step_number": 4,
          "category": "data_analysis",
          "description": "In the second table, percentage values of individual genera are plotted against the stratigraphic column.",
          "searchable_summary": "plot percentage values of genera against stratigraphic column",
          "inputs": [
            "Excel spreadsheet 2"
          ],
          "outputs": [
            "plotted percentage values"
          ],
          "keywords": [
            "percentage values",
            "genera",
            "stratigraphic column"
          ]
        },
        {
          "step_number": 5,
          "category": "visualization",
          "description": "Construct graphs of percentage distribution of miospore and pollen genera throughout the studied stratigraphic interval.",
          "searchable_summary": "construct graphs of percentage distribution for miospore and pollen genera",
          "inputs": [
            "plotted percentage values"
          ],
          "outputs": [
            "percentage distribution graphs"
          ],
          "keywords": [
            "percentage distribution",
            "miospore",
            "pollen",
            "graphs"
          ]
        }
      ]
    }
  ],
  "source_file": "paleoclimatology/papers-text.md/243736799.md",
  "extracted_at": "/Users/varun/git/paleopal/literature_library"
}