{
  "paper_title": "Shell Morphology Study",
  "methods_found": true,
  "methods": [
    {
      "method_name": "Sample Preparation and Shell Sorting",
      "description": "Procedure for processing bulk sediment samples to isolate and sort Carychium shells for analysis.",
      "steps": [
        {
          "step_number": 1,
          "category": "data_processing",
          "description": "Two 7.5 l bulk samples from the middle of the freshwater layer were sorted by hand,",
          "searchable_summary": "Hand sort bulk sediment samples",
          "inputs": [
            "Bulk sediment samples (7.5 l each)"
          ],
          "outputs": [
            "Hand-sorted sediment samples"
          ],
          "keywords": [
            "sample sorting",
            "sediment processing",
            "hand sorting"
          ]
        },
        {
          "step_number": 2,
          "category": "data_processing",
          "description": "washed through a graded series of sieves,",
          "searchable_summary": "Wash sorted samples through sieves",
          "inputs": [
            "Hand-sorted sediment samples"
          ],
          "outputs": [
            "Washed and sieved sediment samples"
          ],
          "keywords": [
            "sieving",
            "washing",
            "sample preparation"
          ]
        },
        {
          "step_number": 3,
          "category": "data_processing",
          "description": "and allowed to dry for further processing.",
          "searchable_summary": "Dry sieved samples",
          "inputs": [
            "Washed and sieved sediment samples"
          ],
          "outputs": [
            "Dried sediment samples"
          ],
          "keywords": [
            "drying",
            "sample preparation"
          ]
        },
        {
          "step_number": 4,
          "category": "data_processing",
          "description": "Thirty-two Carychium shells were culled from a mixture of other molluscs and debris under a stereomicroscope.",
          "searchable_summary": "Cull target shells from dried sample using stereomicroscope",
          "inputs": [
            "Dried sediment samples",
            "Stereomicroscope"
          ],
          "outputs": [
            "Isolated Carychium shells (32 count)"
          ],
          "keywords": [
            "shell sorting",
            "microscope sorting",
            "sample culling",
            "stereomicroscope"
          ]
        }
      ]
    },
    {
      "method_name": "Shell Morphological Analysis",
      "description": "Assessment of qualitative morphological features and internal structures of Carychium shells using visual inspection and micro-CT imaging.",
      "steps": [
        {
          "step_number": 1,
          "category": "data_analysis",
          "description": "Several qualitative aspects of shell morphology are addressed including peristome shape; whorl profile (whorl convexity); teleoconch sculpture;",
          "searchable_summary": "Assess qualitative shell morphology features (peristome shape, whorl profile, sculpture)",
          "inputs": [
            "Isolated Carychium shells"
          ],
          "outputs": [
            "Qualitative morphological observations"
          ],
          "keywords": [
            "morphological analysis",
            "qualitative assessment",
            "shell morphology"
          ]
        },
        {
          "step_number": 2,
          "category": "data_analysis",
          "description": "development of apertural barriers visible in frontal view, including the presence of a deeply immersed denticle/lamella on the parieto-columellar region of the aperture;",
          "searchable_summary": "Assess apertural barriers in frontal view (including parieto-columellar denticle/lamella)",
          "inputs": [
            "Isolated Carychium shells"
          ],
          "outputs": [
            "Observations on apertural barriers"
          ],
          "keywords": [
            "morphological analysis",
            "apertural barriers",
            "shell anatomy"
          ]
        },
        {
          "step_number": 3,
          "category": "data_analysis",
          "description": "development of the columellar lamella as discernable in the micro-CT scans of the ventral, dorsal, side-left, side-right and umbilical perspectives of the adult shell.",
          "searchable_summary": "Assess columellar lamella development using micro-CT scans from multiple perspectives (ventral, dorsal, side-left, side-right, umbilical)",
          "inputs": [
            "Micro-CT scans of shells"
          ],
          "outputs": [
            "Observations on columellar lamella development"
          ],
          "keywords": [
            "micro-CT analysis",
            "columellar lamella",
            "shell anatomy",
            "3D imaging analysis",
            "image perspectives"
          ]
        }
      ]
    }
  ],
  "source_file": "paleoclimatology/papers-text.md/259230940.md",
  "extracted_at": "/Users/varun/git/paleopal/literature_library"
}