{
  "paper_title": "inferred title or filename",
  "methods_found": true,
  "methods": [
    {
      "method_name": "Fossil Assemblage Measurement",
      "description": "Process for measuring and assessing dental patterns of fossil assemblages using stereomicroscopy and scanning electron microscopy.",
      "steps": [
        {
          "step_number": 1,
          "category": "data_fetch",
          "description": "The fossil assemblages of Hayranlı consist of screen-washed material recovered during two different field campaigns.",
          "searchable_summary": "collect fossil assemblages from field campaigns",
          "inputs": [
            "field campaign data"
          ],
          "outputs": [
            "fossil assemblages"
          ],
          "keywords": [
            "fossil collection",
            "field campaign"
          ]
        },
        {
          "step_number": 2,
          "category": "data_processing",
          "description": "Seventy-three isolated cheek teeth were measured and dental patterns were assessed.",
          "searchable_summary": "measure isolated cheek teeth and assess dental patterns",
          "inputs": [
            "isolated cheek teeth"
          ],
          "outputs": [
            "dental measurements",
            "dental patterns"
          ],
          "keywords": [
            "dental measurement",
            "cheek teeth"
          ]
        },
        {
          "step_number": 3,
          "category": "data_processing",
          "description": "Measurements of the specimens were taken using an Olympus SZX10 stereomicroscope in mm units.",
          "searchable_summary": "use stereomicroscope to measure specimens",
          "inputs": [
            "specimens"
          ],
          "outputs": [
            "specimen measurements"
          ],
          "keywords": [
            "stereomicroscope",
            "specimen measurement"
          ]
        },
        {
          "step_number": 4,
          "category": "data_processing",
          "description": "Scanning electron images of the specimens were taken using the JXA-8600 Jeol electron probe.",
          "searchable_summary": "capture scanning electron images of specimens",
          "inputs": [
            "specimens"
          ],
          "outputs": [
            "scanning electron images"
          ],
          "keywords": [
            "scanning electron microscopy",
            "electron probe"
          ]
        }
      ]
    },
    {
      "method_name": "Spatial Distribution Mapping",
      "description": "Mapping spatial distribution of specific species using data from the NOW database and GIS software.",
      "steps": [
        {
          "step_number": 1,
          "category": "data_fetch",
          "description": "Data gathered from New and Old World (NOW) database of Neogene fossil mammal localities and species of Eurasia.",
          "searchable_summary": "download data from NOW database",
          "inputs": [
            "NOW database"
          ],
          "outputs": [
            "fossil mammal data"
          ],
          "keywords": [
            "NOW database",
            "fossil data"
          ]
        },
        {
          "step_number": 2,
          "category": "visualization",
          "description": "Data were used to map spatial distribution of Microdyromys, Peridyromys, and Myomimus using Quantum GIS Copiapo 1.6.0 software.",
          "searchable_summary": "map species distribution using GIS software",
          "inputs": [
            "fossil mammal data"
          ],
          "outputs": [
            "species distribution maps"
          ],
          "keywords": [
            "GIS",
            "species distribution"
          ]
        }
      ]
    },
    {
      "method_name": "Microwear Analysis",
      "description": "Analysis of microwear features on selected molars to study dietary habits using scanning electron microscopy and statistical analysis.",
      "steps": [
        {
          "step_number": 1,
          "category": "data_processing",
          "description": "Microwear analysis was conducted on 12 selected second lower molars.",
          "searchable_summary": "conduct microwear analysis on molars",
          "inputs": [
            "second lower molars"
          ],
          "outputs": [
            "microwear data"
          ],
          "keywords": [
            "microwear analysis",
            "molars"
          ]
        },
        {
          "step_number": 2,
          "category": "data_processing",
          "description": "Scratches and pits were measured from scanning electron images taken at x450 magnification.",
          "searchable_summary": "measure scratches and pits from electron images",
          "inputs": [
            "scanning electron images"
          ],
          "outputs": [
            "scratch and pit measurements"
          ],
          "keywords": [
            "scanning electron microscopy",
            "microwear features"
          ]
        },
        {
          "step_number": 3,
          "category": "data_analysis",
          "description": "Microwear features were counted and measured using analySIS work (v.5.0).",
          "searchable_summary": "count and measure microwear features",
          "inputs": [
            "microwear data"
          ],
          "outputs": [
            "microwear feature counts"
          ],
          "keywords": [
            "microwear analysis",
            "feature counting"
          ]
        },
        {
          "step_number": 4,
          "category": "data_analysis",
          "description": "Statistics were calculated with the PAST (v.2.13) program.",
          "searchable_summary": "perform statistical analysis using PAST",
          "inputs": [
            "microwear feature counts"
          ],
          "outputs": [
            "statistical results"
          ],
          "keywords": [
            "statistical analysis",
            "PAST software"
          ]
        },
        {
          "step_number": 5,
          "category": "validation",
          "description": "A univariate analysis of variance (ANOVA) was performed on the four microwear variables.",
          "searchable_summary": "perform ANOVA on microwear variables",
          "inputs": [
            "microwear variables"
          ],
          "outputs": [
            "ANOVA results"
          ],
          "keywords": [
            "ANOVA",
            "microwear variables"
          ]
        }
      ]
    }
  ],
  "source_file": "paleoclimatology/papers-text.md/55009718.md",
  "extracted_at": "/Users/varun/git/paleopal/literature_library"
}