{
  "paper_title": "Field Sampling and SPI Analysis in the Bay of Tunis",
  "methods_found": true,
  "methods": [
    {
      "method_name": "Field Sampling and Laboratory Analysis",
      "description": "Monthly sampling and analysis of sea surface parameters and phytoplankton in the Bay of Tunis to evaluate nutrient inputs and ecological dynamics.",
      "steps": [
        {
          "step_number": 1,
          "category": "data_fetch",
          "description": "Monthly sampling was carried out (December 1993 to November 1995) at nine stations located in the central waters of the Bay of Tunis.",
          "searchable_summary": "conduct monthly sampling at specified stations in the Bay of Tunis",
          "inputs": [
            "sampling stations",
            "sampling schedule"
          ],
          "outputs": [
            "collected water samples"
          ],
          "keywords": [
            "sampling",
            "Bay of Tunis",
            "monthly"
          ]
        },
        {
          "step_number": 2,
          "category": "data_fetch",
          "description": "Eight additional stations were included along the coastline in order to evaluate nutrient inputs of terrestrial origin.",
          "searchable_summary": "include additional coastal stations for sampling",
          "inputs": [
            "coastal stations"
          ],
          "outputs": [
            "additional water samples"
          ],
          "keywords": [
            "coastal",
            "nutrient inputs"
          ]
        },
        {
          "step_number": 3,
          "category": "data_analysis",
          "description": "At each station, sea surface temperature, salinity, ammonium, nitrate, nitrite, phosphate, silicate and chlorophyll a were measured.",
          "searchable_summary": "measure sea surface parameters at each station",
          "inputs": [
            "water samples"
          ],
          "outputs": [
            "temperature data",
            "salinity data",
            "nutrient concentrations"
          ],
          "keywords": [
            "temperature",
            "salinity",
            "nutrients"
          ]
        },
        {
          "step_number": 4,
          "category": "data_processing",
          "description": "Analyses of nutrients were carried out using a spectrophotometric method (model Beckman 36 UV-vis) according to FAO (1975) for nitrite, nitrate, phosphate and silicate, and according to AMINOT & CHAUSSEPIED (1983) for ammonium.",
          "searchable_summary": "analyze nutrient concentrations using spectrophotometry",
          "inputs": [
            "water samples"
          ],
          "outputs": [
            "nutrient analysis results"
          ],
          "keywords": [
            "spectrophotometry",
            "nutrient analysis"
          ]
        },
        {
          "step_number": 5,
          "category": "data_processing",
          "description": "For chlorophyll a analysis, water samples were filtered through Whatman GF/C filters, frozen and measured with a Spectrophotometer (model Beckman 36 UV-vis.) according to the Lorenzen method described in UNESCO (1966).",
          "searchable_summary": "analyze chlorophyll a using spectrophotometry",
          "inputs": [
            "water samples"
          ],
          "outputs": [
            "chlorophyll a concentrations"
          ],
          "keywords": [
            "chlorophyll a",
            "spectrophotometry"
          ]
        },
        {
          "step_number": 6,
          "category": "data_processing",
          "description": "Surface water samples for phytoplankton analysis were fixed with Lugol's iodine solution and sub-samples of 25 ml were analysed under a Leitz inverted microscope following a sedimentation time of 24 h.",
          "searchable_summary": "prepare and analyze phytoplankton samples",
          "inputs": [
            "water samples",
            "Lugol's iodine"
          ],
          "outputs": [
            "phytoplankton analysis results"
          ],
          "keywords": [
            "phytoplankton",
            "microscopy"
          ]
        },
        {
          "step_number": 7,
          "category": "data_analysis",
          "description": "Cells were counted along two diametric transects of the bottom plate for dominant species, and by sweeping the whole surface for rare species (THRONDSEN, 1995).",
          "searchable_summary": "count phytoplankton cells using microscopy",
          "inputs": [
            "phytoplankton samples"
          ],
          "outputs": [
            "phytoplankton cell counts"
          ],
          "keywords": [
            "cell counting",
            "phytoplankton"
          ]
        },
        {
          "step_number": 8,
          "category": "data_fetch",
          "description": "Meteorological data (air temperature and precipitation) were monitored daily at the Tunis Airport meteorological station 10 Km from the sampling stations at 4 m above sea level.",
          "searchable_summary": "collect daily meteorological data",
          "inputs": [
            "meteorological station"
          ],
          "outputs": [
            "air temperature data",
            "precipitation data"
          ],
          "keywords": [
            "meteorological data",
            "air temperature",
            "precipitation"
          ]
        }
      ]
    },
    {
      "method_name": "Use of SPI Analysis",
      "description": "Application of the Specific Preference Index (SPI) to analyze the spatio-temporal distribution of dominant diatom and dinoflagellate species in relation to environmental parameters.",
      "steps": [
        {
          "step_number": 1,
          "category": "data_analysis",
          "description": "The data-base was performed in order to collect enough information related to the phytoplankton dynamics.",
          "searchable_summary": "compile database for phytoplankton dynamics",
          "inputs": [
            "phytoplankton data",
            "environmental parameters"
          ],
          "outputs": [
            "compiled database"
          ],
          "keywords": [
            "database",
            "phytoplankton dynamics"
          ]
        },
        {
          "step_number": 2,
          "category": "modeling",
          "description": "In order to resolve the difficulties we used a new index called Specific Preference Index (SPI).",
          "searchable_summary": "apply SPI to analyze species distribution",
          "inputs": [
            "compiled database"
          ],
          "outputs": [
            "SPI results"
          ],
          "keywords": [
            "SPI",
            "species distribution"
          ]
        },
        {
          "step_number": 3,
          "category": "data_analysis",
          "description": "This index applied to dominant diatoms and dinoflagellates pointed out clearly the seasonal patterns of these species.",
          "searchable_summary": "identify seasonal patterns using SPI",
          "inputs": [
            "SPI results"
          ],
          "outputs": [
            "seasonal patterns"
          ],
          "keywords": [
            "seasonal patterns",
            "diatoms",
            "dinoflagellates"
          ]
        },
        {
          "step_number": 4,
          "category": "validation",
          "description": "The SPI identifies the apparent ecological niches of the selected species characterized by temperature, salinity and nutrients.",
          "searchable_summary": "validate ecological niches using SPI",
          "inputs": [
            "SPI results"
          ],
          "outputs": [
            "ecological niches"
          ],
          "keywords": [
            "ecological niches",
            "SPI"
          ]
        }
      ]
    }
  ],
  "source_file": "paleoclimatology/papers-text.md/86721381.md",
  "extracted_at": "/Users/varun/git/paleopal/literature_library"
}